IntegratedCpuUnits/RAMarray/ram.sv
module ram(input logic clk, write_enable, ram_read,
           input logic [7:0] access_address,
           input logic [15:0] write_data,
           output logic [15:0] data_out); // defines I/O

    // ram will store program vars & results during execution

    logic [15:0] data_RAM [0:7]; // RAM with 256 memory locations, each stores 16 bits
    // the address is 8-bit wide
    int f; // file descriptor for the RAM file
    int i; // for loop to write in file

    initial
    $readmemh("ram_data.txt", data_RAM); // read in the data from the file
        // ram_data.txt file contains the executed program vars & results
        
    always @ (posedge clk) begin
        if (write_enable) begin
            data_RAM[access_address] <= write_data; // write to the RAM at given address
            f = $fopen("ram_data.txt", "w"); // open the file for writing
            for (i = 0; i < 256; i++) begin
                $fwrite(f, "%h \n", data_RAM[i]); // write the data to the file
            end
            $fclose(f); // close the file
        end
    end
    assign data_out = (ram_read==1) ? data_RAM[access_address] : 16'b0; // read from the RAM at given address
        // if ram_read == 1'b1, then data_out is the data at access_address; else, data_out is 0

endmodule

IntegratedCpuUnits/RAMarray/ram_tb.sv
`timescale 1ns/1ps // define timescale 1 ns and resolution 1 ps = 0.001 ns

`include "ram.sv" // include DUT = device under test

module ram_tb; // testbench for testing the ram.sv RAM module - testbench has no I/O

    // define internal vars used in the testbench
    logic clk, write_enable, ram_read;
    logic [7:0] address;
    logic [15:0] write_data, data_out;

    ram dut (clk, write_enable, ram_read, address, write_data, data_out);
    // define the ram.sv as DUT w its I/O

    // initialise clock signal
    always // always executes this loop
    begin
        clk = 1; #10; clk = 0; #10; // 10 ns interval and then CLK changes between high/low
    end // define clk signal as square wave with period 20 ns

    // Self-checking testbench:
    initial // single-pass code block initialisation
    begin
        $dumpfile("ram_tb.vcd"); /* dump var changes of the testbench file 
                                  onto this Variable Dump Changes (vcd) file */
        $dumpvars(0, ram_tb);   /* Specifies to dump into VCD the lvl 0 file (i.e. top-level file) 
                                  w module name rom_tb */

        ram_read = 1; // read from RAM
        write_enable = 1; // enable writing to RAM
        address = 0;
        #5; if (data_out != 16'bx) $display("Error - ROM address 0, %b", data_out); // nothing stored in RAM yet

        #10; // clk = 0 -> no writing yet
        write_data = 16'b0100000000000010; // write to RAM random package
        if (data_out != 16'bx) $display("Error - ROM address 0, %b", data_out); // nothing stored in RAM yet

        #10; // clk = 1 -> now writing
        if (data_out != 16'b0100000000000010) $display("Error - ROM address 0, %b", data_out); // wrong data stored in RAM

        address = 1;
        #20; if (data_out != 16'bx) $display("Error - ROM address 1");

        #10; ram_read = 1'b0; write_data = 16'b0; #5;
        if (data_out != 16'b0) $display("Error - ROM address 1");

        #20; address = 0;
        if (data_out != 16'b0) $display("Error - ROM address 1");
        
        #10; $finish;
        
    end // end stimuli

    initial
    begin
        $monitor("t = %3d, RAM address = %b, RAM Data Out = %b", $time, address, data_out);
        // display timing and vars to the monitor
    end

endmodule

IntegratedCpuUnits/RAMarray/ram_tb.vcd
$date
	Fri Aug 19 02:09:18 2022
$end
$version
	Icarus Verilog
$end
$timescale
	1ps
$end
$scope module ram_tb $end
$var wire 16 ! data_out [15:0] $end
$var reg 8 " address [7:0] $end
$var reg 1 # clk $end
$var reg 1 $ ram_read $end
$var reg 16 % write_data [15:0] $end
$var reg 1 & write_enable $end
$scope module dut $end
$var wire 8 ' access_address [7:0] $end
$var wire 1 # clk $end
$var wire 1 $ ram_read $end
$var wire 16 ( write_data [15:0] $end
$var wire 1 & write_enable $end
$var wire 16 ) data_out [15:0] $end
$var integer 32 * f [31:0] $end
$var integer 32 + i [31:0] $end
$upscope $end
$upscope $end
$enddefinitions $end
#0
$dumpvars
b100000000 +
b10000000000000000000000000000011 *
bx )
bx (
b0 '
1&
bx %
1$
1#
b0 "
bx !
$end
#10000
0#
#15000
b100000000000010 %
b100000000000010 (
#20000
b100000000000010 !
b100000000000010 )
b100000000 +
1#
#25000
b0 !
b0 )
b1 "
b1 '
#30000
0#
#40000
b100000000000010 !
b100000000000010 )
b100000000 +
1#
#50000
0#
#55000
b0 !
b0 )
b0 %
b0 (
0$
#60000
b100000000 +
1#
#70000
0#
#80000
b100000000 +
1#
b0 "
b0 '
