Drafts/3_IntegrateALU-RegFile/alu.sv
module alu(input logic [7:0] a,
            input logic [7:0] b,
            output logic [7:0] ALUResult,
            input logic [1:0] ALUControl); // define I/O
    
    always_comb // combinational block
        case(ALUControl) // define case blocks to execute specific command
            2'b00 : ALUResult = a & b; // logical AND if ALUResult is 00
            2'b01 : ALUResult = a | b; // logical OR if ALUResult is 01
            2'b10 : ALUResult = a + b; // addition if ALUResult is 10
            2'b11 : ALUResult = a - b; // subtraction if ALUResult is 11
            default: ALUResult = 8'bx; // if not from above cases, output X
        endcase

endmodule

Drafts/3_IntegrateALU-RegFile/reg_file.sv
module reg_file(input logic [3:0] RA1, RA2, WA, // addresses
                input logic [7:0] data_in, // data to write
                input logic clk, reset, write_enable, // control signals
                output logic [7:0] data_out1, data_out2); // data to read
                // define I/O

    logic [7:0] rf [0:15]; // initialise register file of 16 8-bit registers
        // so there are 16 regs w 8-bit address each
    
    assign data_out1 = rf[RA1]; // read from register at address RA1 in reg file
    assign data_out2 = rf[RA2]; // read from reg at address RA2 in register file
    
    always_ff @ (posedge clk) // loop for constant assignment on rising CLK edge
        if (write_enable) 
        rf[WA] <= data_in; // write data saved to register w address WA

endmodule

Drafts/3_IntegrateALU-RegFile/reg_file_alu.sv
`include "reg_file.sv" // includes Register File
`include "alu.sv" // includes ALU

module reg_file_alu(input logic [3:0] RA1, RA2, WA,
                    input logic [7:0] external_data_in,
                    input logic [1:0] ALUControl,
                    input logic clk, RegWrite, ALUSrc,
                    output logic [7:0] ALUResult);
                    // define top-level I/O

    logic [7:0] SrcA; // data_out1 of RegFile -> goes to ALU
    logic [7:0] SrcB; // MUX output: data_out2 and external_data_in -> to ALU
    logic [7:0] SrcMux; // define internal var that is 2nd output of RegFile
    logic reset; // unused var but declared as it is an input for the RegFile

    reg_file reg_file(RA1, RA2, WA, ALUResult, clk, reset, RegWrite, SrcA, SrcMux);
        // define implementation of Reg File with correct vars

    assign SrcB = (ALUSrc) ? external_data_in : SrcMux;
        // multiplexer

    alu alu(SrcA, SrcB, ALUResult, ALUControl);
        // define implementation of ALU

endmodule

Drafts/3_IntegrateALU-RegFile/reg_file_alu_tb.sv
`timescale 1ns/1ps // define timescale 1 ns and resolution 1 ps = 0.001 ns

`include "reg_file_alu.sv" // include DUT = device under test
//`include "reg_file.sv" // includes Register File
//`include "alu.sv" // includes ALU

module reg_file_alu_tb; // testbench for testing the reg_file_alu.sv Register File module - testbench has no I/O

    // define internal vars used in the testbench
    logic [3:0] RA1, RA2, WA;
    logic [7:0] external_data_in;
    logic [1:0] ALUControl;
    logic clk, RegWrite, ALUSrc;
    logic [7:0] ALUResult;

    reg_file_alu dut (RA1, RA2, WA, external_data_in, ALUControl, clk, RegWrite, ALUSrc, ALUResult); // define the reg_file.sv as DUT w its I/O
    
    // initialise clock signal
    always // always executes this loop
    begin
        clk = 1; #10; clk = 0; #10; // 10 ns interval and then CLK changes between high/low
    end // define clk signal as square wave with period 20 ns

    // Self-checking testbench:
    initial // single-pass code block initialisation
    begin
        $dumpfile("reg_file_alu_tb.vcd"); /* dump var changes of the testbench file 
                                  onto this Variable Dump Changes (vcd) file */
        $dumpvars(0, reg_file_alu_tb);   /* Specifies to dump into VCD the lvl 0 file (i.e. top-level file) 
                                  w module name reg_file_tb */

            // t0, clk = 1
        external_data_in = 0; ALUSrc = 1; ALUControl = 0; // AND operation in ALU with ext_data and RegFile SrcA
        RegWrite = 1; // allow writing
        WA = 15; // write ALUResult = 0 into the 15th register (i.e. 1111 address) -> written as CLK = 1 now
        if (ALUResult != 8'b0) $display("Initial Error writing 0 to ALUResult");

        #25; // t25, clk = 1
        ALUControl = 1; // OR ALU
        RA1 = 15; // SrcA = WD3 = ALUResult = 0, SrcB = external_data_in
        external_data_in = 8'b11111111;
        #1;
        if (ALUResult != external_data_in) $display("%b", ALUResult);

        #19;// t45, clk = 1
        ALUControl = 0; // AND
        external_data_in = 8'b11001110;
        #1;
        if (ALUResult != (8'b11111111 & 8'b11001110)) $display("Error assigning to reg 15");

        #8; // t54, clk = 0
        external_data_in = 8'b00000001;
            // ALUResult = (8'b11111111 & 8'b11001110) & 8'b00000001
            // BUT since clk = 0 this is not written into reg 15
        #1; // t55
        external_data_in = 8'b00000000; // all zeros
        ALUControl = 1; 
            // OR between ALUResult = ((8'b11111111 & 8'b11001110) & 8'b00000001) and 8'b00000000
        #1;
        if (ALUResult != (8'b11111111)) $display("Error - reg 15 updated on clk = 0, %b", ALUResult);
            // reg 15 did not retain its value
        
        #19; // t75
        external_data_in = 0;
        ALUControl = 0;
        WA = 2; // save 0 to reg 2 at t = 80 when clk goes 0->1 rising edge
        #1;
        if (ALUResult != (8'b00000000)) $display("Error - reg 2 not updated with zeros");
        
        #9; // t85
        RA1 = 2;
        ALUControl = 1; // OR
        external_data_in = 8'b11011100; // will save into Reg 2 and update it at t = 100 ns
        #1;
        if (ALUResult != (8'b11011100)) $display("Error - reg 2 not updated with 11011100");

        #19; // 105
        WA = 15;
        RA1 = 15;
        external_data_in = 8'b01010110; // will save into Reg 15 and update it at t = 120 ns
        ALUControl = 0; // AND -> saves 01010110 & 11111111 = 8'b01010110
        #1;
        if (ALUResult != (8'b01010110)) $display("Error - reg 15 not updated with 01010110");

        #19; // 125
        RA2 = 15; // storing 11011100
        RA1 = 2; // storing 01010110

        ALUSrc = 0; // so the ALU tests the 4 operations between 11011100 and 01010110
        #1;
        ALUControl = 0; // AND
        #1; if (ALUResult != 8'b01010100) $display("Error - ALU Operation 00");
        $display("ALU 00: %b", ALUResult);
        #1;
        ALUControl = 1; // OR
        #1; if (ALUResult != 8'b11011110) $display("Error - ALU Operation 01");
        $display("ALU 01: %b", ALUResult);
        #1;
        ALUControl = 2; // ADD
        #1; if (ALUResult != 8'b00110010) $display("Error - ALU Operation 10");
        $display("ALU 10: %b", ALUResult);
        #1;
        ALUControl = 3; // SUBTRACT
        #1; if (ALUResult != 8'b10000110) $display("Error - ALU Operation 11");
        $display("ALU 11: %b", ALUResult);

        // t132
        WA = 6; ALUSrc = 1; ALUControl = 0; external_data_in = 8'b00000000;
        // clk rising edge at 140 ns
        
        #10; // t142 - clk has risen to +ve edge
        RA1 = 6; RegWrite = 0; // will not save into the register as RegWrite de-asserted
        ALUControl = 1; external_data_in = 8'b11111111; // will not save
        #20;
        external_data_in = 10101010; ALUControl = 0; // AND
        #1;
        if (ALUResult != 8'b00000000) $display("Error - Reg 6 updated while RegWrite = 0");
            // the result stored in reg 6 should still be 8'b0 as 8'b1 was not saved in the reg
            // so 10101010 AND 00000000 = 00000000

        #10; $finish;
        
    end // end stimuli

    initial
    begin
        $monitor("t = %3d, RA1=%d | RA2=%d | WA=%d | AC=%d | clk=%b | RW=%b | \
AS=%b || ED = %b | AR = %b\
", $time, RA1, RA2, WA, ALUControl, clk, RegWrite, ALUSrc, external_data_in, ALUResult);
        // display timing and vars to the monitor
    end

endmodule

Drafts/3_IntegrateALU-RegFile/reg_file_alu_tb.vcd
$date
	Mon Feb 28 20:30:05 2022
$end
$version
	Icarus Verilog
$end
$timescale
	1ps
$end
$scope module reg_file_alu_tb $end
$var wire 8 ! ALUResult [7:0] $end
$var reg 2 " ALUControl [1:0] $end
$var reg 1 # ALUSrc $end
$var reg 4 $ RA1 [3:0] $end
$var reg 4 % RA2 [3:0] $end
$var reg 1 & RegWrite $end
$var reg 4 ' WA [3:0] $end
$var reg 1 ( clk $end
$var reg 8 ) external_data_in [7:0] $end
$scope module dut $end
$var wire 2 * ALUControl [1:0] $end
$var wire 1 # ALUSrc $end
$var wire 4 + RA1 [3:0] $end
$var wire 4 , RA2 [3:0] $end
$var wire 1 & RegWrite $end
$var wire 4 - WA [3:0] $end
$var wire 1 ( clk $end
$var wire 8 . external_data_in [7:0] $end
$var wire 8 / SrcMux [7:0] $end
$var wire 8 0 SrcB [7:0] $end
$var wire 8 1 SrcA [7:0] $end
$var wire 8 2 ALUResult [7:0] $end
$var reg 1 3 reset $end
$scope module alu $end
$var wire 2 4 ALUControl [1:0] $end
$var wire 8 5 b [7:0] $end
$var wire 8 6 a [7:0] $end
$var reg 8 7 ALUResult [7:0] $end
$upscope $end
$scope module reg_file $end
$var wire 4 8 RA1 [3:0] $end
$var wire 4 9 RA2 [3:0] $end
$var wire 4 : WA [3:0] $end
$var wire 1 ( clk $end
$var wire 8 ; data_in [7:0] $end
$var wire 8 < data_out1 [7:0] $end
$var wire 8 = data_out2 [7:0] $end
$var wire 1 3 reset $end
$var wire 1 & write_enable $end
$upscope $end
$upscope $end
$upscope $end
$enddefinitions $end
#0
$dumpvars
bx =
bx <
b0 ;
b1111 :
bx 9
bx 8
b0 7
bx 6
b0 5
b0 4
x3
b0 2
bx 1
b0 0
bx /
b0 .
b1111 -
bx ,
bx +
b0 *
b0 )
1(
b1111 '
1&
bx %
bx $
1#
b0 "
b0 !
$end
#10000
0(
#20000
1(
#25000
b11111111 !
b11111111 2
b11111111 7
b11111111 ;
b11111111 0
b11111111 5
b11111111 )
b11111111 .
b0 1
b0 6
b0 <
b1111 $
b1111 +
b1111 8
b1 "
b1 *
b1 4
#30000
0(
#40000
b11111111 1
b11111111 6
b11111111 <
1(
#45000
b11001110 !
b11001110 2
b11001110 7
b11001110 ;
b11001110 0
b11001110 5
b11001110 )
b11001110 .
b0 "
b0 *
b0 4
#50000
0(
#54000
b1 !
b1 2
b1 7
b1 ;
b1 0
b1 5
b1 )
b1 .
#55000
b11111111 !
b11111111 2
b11111111 7
b11111111 ;
b0 0
b0 5
b1 "
b1 *
b1 4
b0 )
b0 .
#60000
1(
#70000
0(
#75000
b0 !
b0 2
b0 7
b0 ;
b10 '
b10 -
b10 :
b0 "
b0 *
b0 4
#80000
1(
#85000
b11011100 !
b11011100 2
b11011100 7
b11011100 ;
b11011100 0
b11011100 5
b11011100 )
b11011100 .
b1 "
b1 *
b1 4
b0 1
b0 6
b0 <
b10 $
b10 +
b10 8
#90000
0(
#100000
b11011100 1
b11011100 6
b11011100 <
1(
#105000
b1010110 !
b1010110 2
b1010110 7
b1010110 ;
b1010110 0
b1010110 5
b0 "
b0 *
b0 4
b1010110 )
b1010110 .
b11111111 1
b11111111 6
b11111111 <
b1111 $
b1111 +
b1111 8
b1111 '
b1111 -
b1111 :
#110000
0(
#120000
b1010110 1
b1010110 6
b1010110 <
1(
#125000
b1010100 !
b1010100 2
b1010100 7
b1010100 ;
0#
b11011100 1
b11011100 6
b11011100 <
b10 $
b10 +
b10 8
b1010110 /
b1010110 =
b1111 %
b1111 ,
b1111 9
#128000
b11011110 !
b11011110 2
b11011110 7
b11011110 ;
b1 "
b1 *
b1 4
#130000
b110010 !
b110010 2
b110010 7
b110010 ;
b10 "
b10 *
b10 4
0(
#132000
b10000110 !
b10000110 2
b10000110 7
b10000110 ;
b11 "
b11 *
b11 4
#133000
b0 !
b0 2
b0 7
b0 ;
b0 0
b0 5
b0 )
b0 .
b0 "
b0 *
b0 4
1#
b110 '
b110 -
b110 :
#140000
1(
#143000
b11111111 !
b11111111 2
b11111111 7
b11111111 ;
b11111111 0
b11111111 5
b11111111 )
b11111111 .
b1 "
b1 *
b1 4
0&
b0 1
b0 6
b0 <
b110 $
b110 +
b110 8
#150000
0(
#160000
1(
#163000
b0 !
b0 2
b0 7
b0 ;
b10010 0
b10010 5
b0 "
b0 *
b0 4
b10010 )
b10010 .
