CPU/alu.sv
module alu(input logic [15:0] a,
            input logic [15:0] b,
            input logic [2:0] ALUControl,
            output logic [15:0] ALUResult,
            output logic zero); // define I/O
    
    always_comb // combinational block
        case(ALUControl) // define case blocks to execute specific command
            3'b000 : ALUResult = a + b; // addition if ALUResult is 0
            3'b001 : ALUResult = a - b; // subtraction if ALUResult is 1
            3'b010 : ALUResult = ~a; // logical NOT gate if ALUResult is 2
            3'b011 : ALUResult = a << b; // bitwise leftshift if ALUResult is 3
            3'b100 : ALUResult = a >> b; // bitwise rightshift if ALUResult is 4
            3'b101 : ALUResult = a & b; // logical AND if ALUResult is 5
            3'b110 : ALUResult = a | b; // logical OR if ALUResult is 6
            3'b111 : ALUResult = (a<b) ? 16'b1 : 16'b0; // logical less than if ALUResult is 7
            default: ALUResult = a + b; // if not from above cases, output a+b default operation
        endcase

    assign zero = (ALUResult == 0) ? 1'b1 : 1'b0; // if ALUResult is 0, output 1 else output 0 in zero var

endmodule

IntegratedCpuUnits/ALU/alu_tb.sv
`timescale 1ns/1ps // define timescale 1 ns and resolution 1 ps = 0.001 ns

`include "alu.sv" // include DUT = device under test

module alu_tb; // testbench for testing the alu.sv ALU module - testbench has no I/O

    logic [15:0] a, b, ALUResult;
    logic [2:0] ALUControl;    
    logic zero; // define internal vars used in the testbench
    alu dut ({a[15:0]}, {b[15:0]}, {ALUControl[2:0]}, {ALUResult[15:0]}, zero); // define the alu.sv as DUT (named locally) w its I/O

    initial // single-pass code block initialisation
    begin
        $dumpfile("alu_tb.vcd"); /* dump var changes of the testbench file 
                                  onto this Variable Dump Changes (vcd) file */
        $dumpvars(0, alu_tb);    /* Specifies to dump into VCD the lvl 0 file (i.e. top-level file) 
                                  w module name alu_tb */

        a[15:0] = 16'b0000000011011100; b[15:0] = 16'b0000000001010110; // output now should be 100110010
        // (ALUControl not yet provided so default ALU case - addition)
        #5; if (ALUResult != 16'b0000000100110010) $display("ALU testbench FAILED"); // check the result of the ALU
        #10;
        ALUControl[2:0] = 3'b000; // output should be ALUResult = 100110010 (TC addition), zero=0
        #5; if (ALUResult != 16'b0000000100110010) $display("ALU testbench FAILED"); // check the result of the ALU
        #10;
        ALUControl[2:0] = 3'b001; // output ALUResult = 10000110, zero=0
        #5; if (ALUResult != 16'b0000000010000110) $display("ALU testbench FAILED"); // check the result of the ALU
        #10;
        ALUControl[2:0] = 3'b010; // output ALUResult = 1111111100100011, zero=0
        #5; if (ALUResult != 16'b1111111100100011) $display("ALU testbench FAILED"); // check the result of the ALU
        #10;
        b[15:0] = 16'b0000000000000010;
        ALUControl[2:0] = 3'b011; // output ALUResult = 0000001101110000 (left shift by 2)
        #5; if (ALUResult != 16'b0000001101110000) $display("ALU testbench FAILED"); // check the result of the ALU
        #10;
        ALUControl[2:0] = 3'b100; // output ALUResult = 0000000000110111 (right shift by 2)
        #5; if (ALUResult != 16'b0000000000110111) $display("ALU testbench FAILED"); // check the result of the ALU
        #10;
        b[15:0] = 16'b0000000001010110; ALUControl[2:0] = 3'b101; // output ALUResult = 0000000001010100 (AND)
        #5; if (ALUResult != 16'b0000000001010100) $display("ALU testbench FAILED"); // check the result of the ALU
        #10;
        ALUControl[2:0] = 3'b110; // output ALUResult = 0000000011011110 (OR)
        #5; if (ALUResult != 16'b0000000011011110) $display("ALU testbench FAILED"); // check the result of the ALU
        #10;
        ALUControl[2:0] = 3'b111; // output ALUResult = 0 since a ~< b, zero = 1
        #5; if (ALUResult != 16'b0 || zero != 1'b1) $display("ALU testbench FAILED"); // check the result of the ALU
        #10;
        a[15:0] = 16'b0000000011111111; b[15:0] = 16'b0000000011111111; ALUControl[2:0] = 3'b001; // zero = 1
        #5; if (ALUResult != 16'b0 || zero != 1'b1) $display("ALU testbench FAILED"); // check the result of the ALU
        #10; $finish;
        
    end // end stimuli

    initial
    begin
        $monitor("t = %3d, a = %b | b = %b | ALUControl = %2b | ALUResult = %b | zero = %b", $time, a, b, ALUControl, ALUResult, zero);
        // display timing and vars a, b, ALUResult to the monitor
    end

endmodule

IntegratedCpuUnits/ALU/alu_tb.vcd
$date
	Wed Aug 24 01:44:54 2022
$end
$version
	Icarus Verilog
$end
$timescale
	1ps
$end
$scope module alu_tb $end
$var wire 1 ! zero $end
$var wire 16 " ALUResult [15:0] $end
$var reg 3 # ALUControl [2:0] $end
$var reg 16 $ a [15:0] $end
$var reg 16 % b [15:0] $end
$scope module dut $end
$var wire 3 & ALUControl [2:0] $end
$var wire 16 ' a [15:0] $end
$var wire 16 ( b [15:0] $end
$var wire 1 ! zero $end
$var reg 16 ) ALUResult [15:0] $end
$upscope $end
$upscope $end
$enddefinitions $end
#0
$dumpvars
b100110010 )
b1010110 (
b11011100 '
bx &
b1010110 %
b11011100 $
bx #
b100110010 "
0!
$end
#15000
b0 &
b0 #
#30000
b10000110 "
b10000110 )
b1 &
b1 #
#45000
b1111111100100011 "
b1111111100100011 )
b10 &
b10 #
#60000
b1101110000 "
b1101110000 )
b11 &
b11 #
b10 (
b10 %
#75000
b110111 "
b110111 )
b100 &
b100 #
#90000
b1010100 "
b1010100 )
b101 &
b101 #
b1010110 (
b1010110 %
#105000
b11011110 "
b11011110 )
b110 &
b110 #
#120000
1!
b0 "
b0 )
b111 &
b111 #
#135000
b1 &
b1 #
b11111111 (
b11111111 %
b11111111 '
b11111111 $
