CPU/risc_control.sv
module risc_control(input logic [3:0] opcode, /* opcode output from DataBus */
                    output logic [1:0] alu_op, /* ALU operation */
                    output logic jmp, beq, ram_read, write_enable, alu_src, dest_reg, mem_to_reg, reg_write, bne /* control signals */);

    always_comb begin
        case(opcode)
            4'b0000:  // LW
                begin
                    dest_reg = 1'b0;
                    alu_src = 1'b1;
                    mem_to_reg = 1'b1;
                    reg_write = 1'b1;
                    ram_read = 1'b1;
                    write_enable = 1'b0;
                    beq = 1'b0;
                    bne = 1'b0;
                    alu_op = 2'b10;
                    jmp = 1'b0;   
                end
            4'b0001:  // SW
                begin
                    dest_reg = 1'b0;
                    alu_src = 1'b1;
                    mem_to_reg = 1'b0;
                    reg_write = 1'b0;
                    ram_read = 1'b0;
                    write_enable = 1'b1;
                    beq = 1'b0;
                    bne = 1'b0;
                    alu_op = 2'b10;
                    jmp = 1'b0;   
                end
            4'b0010:  // data_processing
                begin
                    dest_reg = 1'b1;
                    alu_src = 1'b0;
                    mem_to_reg = 1'b0;
                    reg_write = 1'b1;
                    ram_read = 1'b0;
                    write_enable = 1'b0;
                    beq = 1'b0;
                    bne = 1'b0;
                    alu_op = 2'b00;
                    jmp = 1'b0;   
                end
            4'b0011:  // data_processing
                begin
                    dest_reg = 1'b1;
                    alu_src = 1'b0;
                    mem_to_reg = 1'b0;
                    reg_write = 1'b1;
                    ram_read = 1'b0;
                    write_enable = 1'b0;
                    beq = 1'b0;
                    bne = 1'b0;
                    alu_op = 2'b00;
                    jmp = 1'b0;   
                end
            4'b0100:  // data_processing
                begin
                    dest_reg = 1'b1;
                    alu_src = 1'b0;
                    mem_to_reg = 1'b0;
                    reg_write = 1'b1;
                    ram_read = 1'b0;
                    write_enable = 1'b0;
                    beq = 1'b0;
                    bne = 1'b0;
                    alu_op = 2'b00;
                    jmp = 1'b0;   
                end
            4'b0101:  // data_processing
                begin
                    dest_reg = 1'b1;
                    alu_src = 1'b0;
                    mem_to_reg = 1'b0;
                    reg_write = 1'b1;
                    ram_read = 1'b0;
                    write_enable = 1'b0;
                    beq = 1'b0;
                    bne = 1'b0;
                    alu_op = 2'b00;
                    jmp = 1'b0;   
                end
            4'b0110:  // data_processing
                begin
                    dest_reg = 1'b1;
                    alu_src = 1'b0;
                    mem_to_reg = 1'b0;
                    reg_write = 1'b1;
                    ram_read = 1'b0;
                    write_enable = 1'b0;
                    beq = 1'b0;
                    bne = 1'b0;
                    alu_op = 2'b00;
                    jmp = 1'b0;   
                end
            4'b0111:  // data_processing
                begin
                    dest_reg = 1'b1;
                    alu_src = 1'b0;
                    mem_to_reg = 1'b0;
                    reg_write = 1'b1;
                    ram_read = 1'b0;
                    write_enable = 1'b0;
                    beq = 1'b0;
                    bne = 1'b0;
                    alu_op = 2'b00;
                    jmp = 1'b0;   
                end
            4'b1000:  // data_processing
                begin
                    dest_reg = 1'b1;
                    alu_src = 1'b0;
                    mem_to_reg = 1'b0;
                    reg_write = 1'b1;
                    ram_read = 1'b0;
                    write_enable = 1'b0;
                    beq = 1'b0;
                    bne = 1'b0;
                    alu_op = 2'b00;
                    jmp = 1'b0;   
                end
            4'b1001:  // data_processing
                begin
                    dest_reg = 1'b1;
                    alu_src = 1'b0;
                    mem_to_reg = 1'b0;
                    reg_write = 1'b1;
                    ram_read = 1'b0;
                    write_enable = 1'b0;
                    beq = 1'b0;
                    bne = 1'b0;
                    alu_op = 2'b00;
                    jmp = 1'b0;   
                end
            4'b1011:  // BEQ
                begin
                    dest_reg = 1'b0;
                    alu_src = 1'b0;
                    mem_to_reg = 1'b0;
                    reg_write = 1'b0;
                    ram_read = 1'b0;
                    write_enable = 1'b0;
                    beq = 1'b1;
                    bne = 1'b0;
                    alu_op = 2'b01;
                    jmp = 1'b0;   
                end
            4'b1100:  // BNE
                begin
                    dest_reg = 1'b0;
                    alu_src = 1'b0;
                    mem_to_reg = 1'b0;
                    reg_write = 1'b0;
                    ram_read = 1'b0;
                    write_enable = 1'b0;
                    beq = 1'b0;
                    bne = 1'b1;
                    alu_op = 2'b01;
                    jmp = 1'b0;   
                end
            4'b1101:  // jmp
                begin
                    dest_reg = 1'b0;
                    alu_src = 1'b0;
                    mem_to_reg = 1'b0;
                    reg_write = 1'b0;
                    ram_read = 1'b0;
                    write_enable = 1'b0;
                    beq = 1'b0;
                    bne = 1'b0;
                    alu_op = 2'b00;
                    jmp = 1'b1;   
                end   
            default:
                begin
                    dest_reg = 1'b1;
                    alu_src = 1'b0;
                    mem_to_reg = 1'b0;
                    reg_write = 1'b1;
                    ram_read = 1'b0;
                    write_enable = 1'b0;
                    beq = 1'b0;
                    bne = 1'b0;
                    alu_op = 2'b00;
                    jmp = 1'b0; 
                end
        endcase
    end

endmodule

IntegratedCpuUnits/ControlUnit/risc_control_tb.sv
`timescale 1ns/1ps // define timescale 1 ns and resolution 1 ps = 0.001 ns

`include "risc_control.sv" // include DUT = device under test

module risc_control_tb; // testbench for testing the risc_control.sv ROM module - testbench has no I/O

    // define internal vars used in the testbench
    logic [3:0] opcode;
    logic [1:0] alu_op;
    logic jmp, beq, ram_read, write_enable, alu_src, dest_reg, mem_to_reg, reg_write, bne;

    logic condition1, condition2, condition3; // for self-checking testbench readability -- break up long conditional
    logic [5:0] tests_passed = 5'b0; // counter for tests successfully passed

    risc_control dut (opcode, alu_op, jmp, beq, ram_read, write_enable, alu_src, dest_reg, mem_to_reg, reg_write, bne);
    // define the risc_control.sv as DUT w its I/O

    // Self-checking testbench:
    initial // single-pass code block initialisation
    begin
        $dumpfile("risc_control_tb.vcd"); /* dump var changes of the testbench file 
                                  onto this Variable Dump Changes (vcd) file */
        $dumpvars(0, risc_control_tb);   /* Specifies to dump into VCD the lvl 0 file (i.e. top-level file) 
                                  w module name risc_control_tb */

        #10; // opcode = 4'bx now so the default case is active
        condition1 = dest_reg == 1'b1 & alu_src == 1'b0 & mem_to_reg == 1'b0 & reg_write == 1'b1;
        condition2 = ram_read == 1'b0 & write_enable == 1'b0 & beq == 1'b0 & bne == 1'b0;
        condition3 = alu_op == 2'b00 & jmp == 1'b0;
        if (condition1 & condition2 & condition3) $display("opcode X PASS");
        if (condition1 & condition2 & condition3) tests_passed = tests_passed + 5'b1;
 
        #10; opcode = 4'b0000; // opcode = 0
        // still default case active as opcode was just updated
        if (condition1 & condition2 & condition3) $display("opcode X PASS (2nd time)");
        if (condition1 & condition2 & condition3) tests_passed = tests_passed + 5'b1;

        #1; // opcode updated and case statement executed for opcode = 0
        condition1 = dest_reg == 1'b0 & alu_src == 1'b1 & mem_to_reg == 1'b1 & reg_write == 1'b1;
        condition2 = ram_read == 1'b1 & write_enable == 1'b0 & beq == 1'b0 & bne == 1'b0;
        condition3 = alu_op == 2'b10 & jmp == 1'b0;
        if (condition1 & condition2 & condition3) $display("opcode 0 PASS");
        if (condition1 & condition2 & condition3) tests_passed = tests_passed + 5'b1;

        opcode = 4'b0001; #1; // opcode = 1 and case statement executed
        condition1 = dest_reg == 1'b0 & alu_src == 1'b1 & mem_to_reg == 1'b0 & reg_write == 1'b0;
        condition2 = ram_read == 1'b0 & write_enable == 1'b1 & beq == 1'b0 & bne == 1'b0;
        condition3 = alu_op == 2'b10 & jmp == 1'b0;
        if (condition1 & condition2 & condition3) $display("opcode 1 PASS");
        if (condition1 & condition2 & condition3) tests_passed = tests_passed + 5'b1;

        opcode = 4'b0010; #1;
        condition1 = dest_reg == 1'b1 & alu_src == 1'b0 & mem_to_reg == 1'b0 & reg_write == 1'b1;
        condition2 = ram_read == 1'b0 & write_enable == 1'b0 & beq == 1'b0 & bne == 1'b0;
        condition3 = alu_op == 2'b00 & jmp == 1'b0;
        if (condition1 & condition2 & condition3) $display("opcode 2 PASS");
        if (condition1 & condition2 & condition3) tests_passed = tests_passed + 5'b1;

        opcode = 4'b0011; #1;
        condition1 = dest_reg == 1'b1 & alu_src == 1'b0 & mem_to_reg == 1'b0 & reg_write == 1'b1;
        condition2 = ram_read == 1'b0 & write_enable == 1'b0 & beq == 1'b0 & bne == 1'b0;
        condition3 = alu_op == 2'b00 & jmp == 1'b0;
        if (condition1 & condition2 & condition3) $display("opcode 3 PASS");
        if (condition1 & condition2 & condition3) tests_passed = tests_passed + 5'b1;

        opcode = 4'b0100; #1;
        condition1 = dest_reg == 1'b1 & alu_src == 1'b0 & mem_to_reg == 1'b0 & reg_write == 1'b1;
        condition2 = ram_read == 1'b0 & write_enable == 1'b0 & beq == 1'b0 & bne == 1'b0;
        condition3 = alu_op == 2'b00 & jmp == 1'b0;
        if (condition1 & condition2 & condition3) $display("opcode 4 PASS");
        if (condition1 & condition2 & condition3) tests_passed = tests_passed + 5'b1;

        opcode = 4'b0101; #1;
        condition1 = dest_reg == 1'b1 & alu_src == 1'b0 & mem_to_reg == 1'b0 & reg_write == 1'b1;
        condition2 = ram_read == 1'b0 & write_enable == 1'b0 & beq == 1'b0 & bne == 1'b0;
        condition3 = alu_op == 2'b00 & jmp == 1'b0;
        if (condition1 & condition2 & condition3) $display("opcode 5 PASS");
        if (condition1 & condition2 & condition3) tests_passed = tests_passed + 5'b1;

        opcode = 4'b0110; #1;
        condition1 = dest_reg == 1'b1 & alu_src == 1'b0 & mem_to_reg == 1'b0 & reg_write == 1'b1;
        condition2 = ram_read == 1'b0 & write_enable == 1'b0 & beq == 1'b0 & bne == 1'b0;
        condition3 = alu_op == 2'b00 & jmp == 1'b0;
        if (condition1 & condition2 & condition3) $display("opcode 6 PASS");
        if (condition1 & condition2 & condition3) tests_passed = tests_passed + 5'b1;

        opcode = 4'b0111; #1;
        condition1 = dest_reg == 1'b1 & alu_src == 1'b0 & mem_to_reg == 1'b0 & reg_write == 1'b1;
        condition2 = ram_read == 1'b0 & write_enable == 1'b0 & beq == 1'b0 & bne == 1'b0;
        condition3 = alu_op == 2'b00 & jmp == 1'b0;
        if (condition1 & condition2 & condition3) $display("opcode 7 PASS");
        if (condition1 & condition2 & condition3) tests_passed = tests_passed + 5'b1;

        opcode = 4'b1000; #1;
        condition1 = dest_reg == 1'b1 & alu_src == 1'b0 & mem_to_reg == 1'b0 & reg_write == 1'b1;
        condition2 = ram_read == 1'b0 & write_enable == 1'b0 & beq == 1'b0 & bne == 1'b0;
        condition3 = alu_op == 2'b00 & jmp == 1'b0;
        if (condition1 & condition2 & condition3) $display("opcode 8 PASS");
        if (condition1 & condition2 & condition3) tests_passed = tests_passed + 5'b1;

        opcode = 4'b1001; #1;
        condition1 = dest_reg == 1'b1 & alu_src == 1'b0 & mem_to_reg == 1'b0 & reg_write == 1'b1;
        condition2 = ram_read == 1'b0 & write_enable == 1'b0 & beq == 1'b0 & bne == 1'b0;
        condition3 = alu_op == 2'b00 & jmp == 1'b0;
        if (condition1 & condition2 & condition3) $display("opcode 9 PASS");
        if (condition1 & condition2 & condition3) tests_passed = tests_passed + 5'b1;

        opcode = 4'b1010; #1; // default case
        condition1 = dest_reg == 1'b1 & alu_src == 1'b0 & mem_to_reg == 1'b0 & reg_write == 1'b1;
        condition2 = ram_read == 1'b0 & write_enable == 1'b0 & beq == 1'b0 & bne == 1'b0;
        condition3 = alu_op == 2'b00 & jmp == 1'b0;
        if (condition1 & condition2 & condition3) $display("opcode X PASS (3rd time 10)");
        if (condition1 & condition2 & condition3) tests_passed = tests_passed + 5'b1;
        
        opcode = 4'b1011; #1; // default case
        condition1 = dest_reg == 1'b0 & alu_src == 1'b0 & mem_to_reg == 1'b0 & reg_write == 1'b0;
        condition2 = ram_read == 1'b0 & write_enable == 1'b0 & beq == 1'b1 & bne == 1'b0;
        condition3 = alu_op == 2'b01 & jmp == 1'b0;
        if (condition1 & condition2 & condition3) $display("opcode 11 PASS");
        if (condition1 & condition2 & condition3) tests_passed = tests_passed + 5'b1;

        opcode = 4'b1100; #1; // default case
        condition1 = dest_reg == 1'b0 & alu_src == 1'b0 & mem_to_reg == 1'b0 & reg_write == 1'b0;
        condition2 = ram_read == 1'b0 & write_enable == 1'b0 & beq == 1'b0 & bne == 1'b1;
        condition3 = alu_op == 2'b01 & jmp == 1'b0;
        if (condition1 & condition2 & condition3) $display("opcode 12 PASS");
        if (condition1 & condition2 & condition3) tests_passed = tests_passed + 5'b1;

        opcode = 4'b1101; #1; // default case
        condition1 = dest_reg == 1'b0 & alu_src == 1'b0 & mem_to_reg == 1'b0 & reg_write == 1'b0;
        condition2 = ram_read == 1'b0 & write_enable == 1'b0 & beq == 1'b0 & bne == 1'b0;
        condition3 = alu_op == 2'b00 & jmp == 1'b1;
        if (condition1 & condition2 & condition3) $display("opcode 13 PASS");
        if (condition1 & condition2 & condition3) tests_passed = tests_passed + 5'b1;

        opcode = 4'b1110; #1; // default case
        condition1 = dest_reg == 1'b1 & alu_src == 1'b0 & mem_to_reg == 1'b0 & reg_write == 1'b1;
        condition2 = ram_read == 1'b0 & write_enable == 1'b0 & beq == 1'b0 & bne == 1'b0;
        condition3 = alu_op == 2'b00 & jmp == 1'b0;
        if (condition1 & condition2 & condition3) $display("opcode X PASS (4th time 14)");
        if (condition1 & condition2 & condition3) tests_passed = tests_passed + 5'b1;

        opcode = 4'b1010; #1; // default case
        condition1 = dest_reg == 1'b1 & alu_src == 1'b0 & mem_to_reg == 1'b0 & reg_write == 1'b1;
        condition2 = ram_read == 1'b0 & write_enable == 1'b0 & beq == 1'b0 & bne == 1'b0;
        condition3 = alu_op == 2'b00 & jmp == 1'b0;
        if (condition1 & condition2 & condition3) $display("opcode X PASS (5th time 15)");
        if (condition1 & condition2 & condition3) tests_passed = tests_passed + 5'b1;

        if (tests_passed == 5'b10010) $display("\nALL TESTS PASSED");
        else $display("TESTS FAILED");

        $finish;
        
    end // end stimuli

    initial
    begin
        // display timing and vars to the monitor
    end

endmodule

IntegratedCpuUnits/ControlUnit/risc_control_tb.vcd
$date
	Sat Sep 24 02:47:46 2022
$end
$version
	Icarus Verilog
$end
$timescale
	1ps
$end
$scope module risc_control_tb $end
$var wire 1 ! write_enable $end
$var wire 1 " reg_write $end
$var wire 1 # ram_read $end
$var wire 1 $ mem_to_reg $end
$var wire 1 % jmp $end
$var wire 1 & dest_reg $end
$var wire 1 ' bne $end
$var wire 1 ( beq $end
$var wire 1 ) alu_src $end
$var wire 2 * alu_op [1:0] $end
$var reg 1 + condition1 $end
$var reg 1 , condition2 $end
$var reg 1 - condition3 $end
$var reg 4 . opcode [3:0] $end
$var reg 6 / tests_passed [5:0] $end
$scope module dut $end
$var wire 4 0 opcode [3:0] $end
$var reg 2 1 alu_op [1:0] $end
$var reg 1 ) alu_src $end
$var reg 1 ( beq $end
$var reg 1 ' bne $end
$var reg 1 & dest_reg $end
$var reg 1 % jmp $end
$var reg 1 $ mem_to_reg $end
$var reg 1 # ram_read $end
$var reg 1 " reg_write $end
$var reg 1 ! write_enable $end
$upscope $end
$upscope $end
$enddefinitions $end
#0
$dumpvars
b0 1
bx 0
b0 /
bx .
x-
x,
x+
b0 *
0)
0(
0'
1&
0%
0$
0#
1"
0!
$end
#10000
b1 /
1-
1,
1+
#20000
b10 *
b10 1
1#
1$
1)
0&
b10 /
b0 .
b0 0
#21000
1!
0#
0"
0$
b1 .
b1 0
b11 /
#22000
b0 *
b0 1
0!
1"
0)
1&
b10 .
b10 0
b100 /
#23000
b11 .
b11 0
b101 /
#24000
b100 .
b100 0
b110 /
#25000
b101 .
b101 0
b111 /
#26000
b110 .
b110 0
b1000 /
#27000
b111 .
b111 0
b1001 /
#28000
b1000 .
b1000 0
b1010 /
#29000
b1001 .
b1001 0
b1011 /
#30000
b1010 .
b1010 0
b1100 /
#31000
b1 *
b1 1
1(
0"
0&
b1011 .
b1011 0
b1101 /
#32000
1'
0(
b1100 .
b1100 0
b1110 /
#33000
1%
b0 *
b0 1
0'
b1101 .
b1101 0
b1111 /
#34000
0%
1"
1&
b1110 .
b1110 0
b10000 /
#35000
b1010 .
b1010 0
b10001 /
#36000
b10010 /
